astro_pi-1.1.8.dist-info/WHEEL
astro_pi-1.1.8.dist-info/RECORD
astro_pi-1.1.8.dist-info/top_level.txt
astro_pi-1.1.8.dist-info/metadata.json
astro_pi-1.1.8.dist-info/METADATA
astro_pi-1.1.8.dist-info/DESCRIPTION.rst
astro_pi/astro_pi.py
astro_pi/astro_pi_text.png
astro_pi/__init__.py
astro_pi/astro_pi_text.txt
