Metadata-Version: 2.0
Name: astro-pi
Version: 1.1.8
Summary: Python API for Astro Pi (Sense HAT) for the Raspberry Pi
Home-page: https://github.com/astro-pi/astro-pi-hat
Author: Dave Honess
Author-email: dave@raspberrypi.org
License: BSD
Keywords: raspberrypi,astro pi,astro pi hat,sense hat
Platform: UNKNOWN
Classifier: Development Status :: 7 - Inactive
Classifier: Programming Language :: Python :: 2
Classifier: Programming Language :: Python :: 3
Classifier: Topic :: Scientific/Engineering :: Astronomy
Classifier: Topic :: Scientific/Engineering :: Atmospheric Science
Classifier: Topic :: Education
Classifier: Intended Audience :: Education
Classifier: Intended Audience :: Science/Research
Classifier: License :: OSI Approved :: BSD License
Requires-Dist: pillow
Requires-Dist: numpy
